fibonacci_sum/__init__.py
fibonacci_sum/fibonacci_sum.py
fibonacci_sum-0.0.3.dist-info/LICENCE
fibonacci_sum-0.0.3.dist-info/METADATA
fibonacci_sum-0.0.3.dist-info/WHEEL
fibonacci_sum-0.0.3.dist-info/top_level.txt
fibonacci_sum-0.0.3.dist-info/RECORD
