Metadata-Version: 2.1
Name: fibonacci-sum
Version: 0.0.3
Summary: Returns the sum of a sequence of Fibonacci
Home-page: https://github.com/MartinsMessias/fibonacci_sum
Author: Messias Martins
Author-email: messiassouzakb@gmail.com
License: UNKNOWN
Project-URL: Bug Tracker, https://github.com/MartinsMessias/fibonacci_sum/issues
Platform: UNKNOWN
Classifier: Programming Language :: Python :: 3
Classifier: License :: OSI Approved :: MIT License
Classifier: Operating System :: OS Independent
Requires-Python: >=3.6
